{
    "metadata": {},
    "startPage": "/first-page",
    "pages": [
        {
            "title": "First page",
            "path": "/first-page",
            "components": [
                {
                    "name": "YFTKhr",
                    "options": {},
                    "type": "RadiosField",
                    "title": "org type",
                    "list": "PaUvtG"
                }
            ],
            "next": [
                {
                    "path": "/org-type-a",
                    "condition": "GDqNNS"
                },
                {
                    "path": "/org-type-b",
                    "condition": "aTqAcd"
                },
                {
                    "path": "/org-type-c",
                    "condition": "LQOPpJ"
                }
            ]
        },
        {
            "title": "Summary",
            "path": "/summary",
            "controller": "./pages/summary.js",
            "components": []
        },
        {
            "path": "/org-type-a",
            "title": "Org Type A",
            "components": [],
            "next": [
                {
                    "path": "/summary"
                }
            ]
        },
        {
            "path": "/org-type-b",
            "title": "Org type B",
            "components": [],
            "next": [
                {
                    "path": "/summary"
                }
            ]
        },
        {
            "path": "/org-type-c",
            "title": "Org type C",
            "components": [],
            "next": [
                {
                    "path": "/summary"
                }
            ]
        }
    ],
    "lists": [
        {
            "title": "org type",
            "name": "PaUvtG",
            "type": "string",
            "items": [
                {
                    "text": "A",
                    "value": "A"
                },
                {
                    "text": "B",
                    "value": "B"
                },
                {
                    "text": "C1",
                    "value": "C1"
                },
                {
                    "text": "C2",
                    "value": "C2"
                }
            ]
        }
    ],
    "sections": [],
    "conditions": [
        {
            "displayName": "org type a",
            "name": "GDqNNS",
            "value": {
                "name": "org type a",
                "conditions": [
                    {
                        "field": {
                            "name": "YFTKhr",
                            "type": "RadiosField",
                            "display": "org type"
                        },
                        "operator": "is",
                        "value": {
                            "type": "Value",
                            "value": "A",
                            "display": "A"
                        }
                    }
                ]
            }
        },
        {
            "displayName": "org type b",
            "name": "aTqAcd",
            "value": {
                "name": "org type b",
                "conditions": [
                    {
                        "field": {
                            "name": "YFTKhr",
                            "type": "RadiosField",
                            "display": "org type"
                        },
                        "operator": "is",
                        "value": {
                            "type": "Value",
                            "value": "B",
                            "display": "B"
                        }
                    }
                ]
            }
        },
        {
            "displayName": "org type c",
            "name": "LQOPpJ",
            "value": {
                "name": "org type c",
                "conditions": [
                    {
                        "field": {
                            "name": "YFTKhr",
                            "type": "RadiosField",
                            "display": "org type"
                        },
                        "operator": "is",
                        "value": {
                            "type": "Value",
                            "value": "C1",
                            "display": "C1"
                        }
                    },
                    {
                        "coordinator": "or",
                        "field": {
                            "name": "YFTKhr",
                            "type": "RadiosField",
                            "display": "org type"
                        },
                        "operator": "is",
                        "value": {
                            "type": "Value",
                            "value": "C2",
                            "display": "C2"
                        }
                    }
                ]
            }
        }
    ],
    "fees": [],
    "outputs": [],
    "version": 2,
    "skipSummary": false,
    "feeOptions": {},
    "markAsComplete": false
}
